worldcoin_wrapper/init.py
worldcoin_wrapper/worldcoin.py
worldcoin_wrapper-1.0.1.dist-info/METADATA
worldcoin_wrapper-1.0.1.dist-info/WHEEL
worldcoin_wrapper-1.0.1.dist-info/top_level.txt
worldcoin_wrapper-1.0.1.dist-info/RECORD
