Metadata-Version: 2.1
Name: worldcoin-wrapper
Version: 1.0.1
Summary: Это модуль для упрощенной работы с api WorldCoin
Home-page: https://github.com/Duzive/worldcoin
Author: Duzive
License: Apache License, Version 2.0, see LICENSE file
Download-URL: https://github.com/Duzive/worldcoin/archive/v1.0.1.zip
Platform: UNKNOWN
Classifier: License :: OSI Approved :: Apache Software License
Classifier: Operating System :: OS Independent
Classifier: Programming Language :: Python
Classifier: Programming Language :: Python :: 3.6
Classifier: Programming Language :: Python :: 3.7
Classifier: Programming Language :: Python :: 3.8
Classifier: Programming Language :: Python :: 3.9
Classifier: Programming Language :: Python :: Implementation :: PyPy
Classifier: Programming Language :: Python :: Implementation :: CPython
Requires-Dist: requests
